mlflow_oidc_client/__init__.py
mlflow_oidc_client/config.py
mlflow_oidc_client/oidc_session.py
mlflow_oidc_client/request_header_provider.py
mlflow_oidc_client-0.2.4.dist-info/LICENSE.md
mlflow_oidc_client-0.2.4.dist-info/METADATA
mlflow_oidc_client-0.2.4.dist-info/WHEEL
mlflow_oidc_client-0.2.4.dist-info/entry_points.txt
mlflow_oidc_client-0.2.4.dist-info/RECORD
