Metadata-Version: 2.1
Name: mlflow-oidc-client
Version: 0.2.4
Summary: MLflow plugin adding OIDC/OAuth 2.1 client authorization
Home-page: https://gitlab.com/lzinsou/mlflow-oidc-client
Keywords: mlflow,plugin,mlops,oidc,oauth,oauth2
Author: Loris Zinsou
Author-email: lzinsou@protonmail.com
Requires-Python: >=3.10,<4.0
Classifier: Development Status :: 3 - Alpha
Classifier: Environment :: Plugins
Classifier: Programming Language :: Python :: 3
Classifier: Programming Language :: Python :: 3.10
Classifier: Programming Language :: Python :: 3.11
Requires-Dist: oidc-client (>=0.2.3,<0.3.0)
Requires-Dist: pyjwt (>=2,<3)
Requires-Dist: toml (>=0.10.2,<0.11.0) ; python_version < "3.11"
Requires-Dist: typing-extensions (>=4.0.1) ; python_version < "3.11"
Project-URL: Repository, https://gitlab.com/lzinsou/mlflow-oidc-client
